langchain_lilypad/__init__.py
langchain_lilypad/module.py
langchain_lilypad-0.1.4.dist-info/METADATA
langchain_lilypad-0.1.4.dist-info/WHEEL
langchain_lilypad-0.1.4.dist-info/top_level.txt
langchain_lilypad-0.1.4.dist-info/RECORD
